{
  "timestamp": "2026-03-29T06:57:55.151Z",
  "source": "ai-autonomous-idea-guarded-cycle",
  "selectedCount": 8,
  "nextWave": [
    {
      "id": "autonomous-opportunity-radar",
      "title": "Autonomous Opportunity Radar",
      "shortDescription": "Map your current metrics and constraints to a prioritized roadmap of AI automations, growth loops, and autonomous product upgrades.",
      "status": "live",
      "href": "/ai-lab/autonomous-opportunity-radar",
      "score": 75,
      "priority": "high",
      "reason": "High signal for near-term autonomous promotion and safe deploy velocity."
    },
    {
      "id": "autonomous-incident-commander",
      "title": "Autonomous Incident Commander",
      "shortDescription": "Run incident triage simulations with AI-suggested owner assignment, communication timelines, and rollback readiness.",
      "status": "live",
      "href": "/ai-lab/autonomous-incident-commander",
      "score": 70,
      "priority": "medium",
      "reason": "Useful candidate for incremental evolution cycle with gated validation."
    },
    {
      "id": "ai-site-evolution-advisor",
      "title": "AI Site Evolution Advisor",
      "shortDescription": "Visualize how Zion’s autonomous agents are improving ziontechgroup.com and what they will optimize next.",
      "status": "live",
      "href": "/ai-lab/ai-site-evolution-advisor",
      "score": 69,
      "priority": "medium",
      "reason": "Useful candidate for incremental evolution cycle with gated validation."
    },
    {
      "id": "deployment-readiness-console",
      "title": "Deployment Readiness Console",
      "shortDescription": "Inspect automation, UX, and link-health checks that gate autonomous deploys for ziontechgroup.com.",
      "status": "live",
      "href": "/ai-lab/deployment-readiness-console",
      "score": 69,
      "priority": "medium",
      "reason": "Useful candidate for incremental evolution cycle with gated validation."
    },
    {
      "id": "autonomous-agent-skill-orchestrator",
      "title": "Autonomous Agent Skill Orchestrator",
      "shortDescription": "Plan and score OpenClaw worker skill mixes, cadence, and risk tiers to accelerate autonomous app improvement safely.",
      "status": "live",
      "href": "/ai-lab/autonomous-agent-skill-orchestrator",
      "score": 69,
      "priority": "medium",
      "reason": "Useful candidate for incremental evolution cycle with gated validation."
    },
    {
      "id": "autonomous-experiment-priority-engine",
      "title": "Autonomous Experiment Priority Engine",
      "shortDescription": "Prioritize AI experiments by expected lift, confidence, and execution risk to accelerate autonomous app improvements.",
      "status": "live",
      "href": "/ai-lab/autonomous-experiment-priority-engine",
      "score": 69,
      "priority": "medium",
      "reason": "Useful candidate for incremental evolution cycle with gated validation."
    },
    {
      "id": "deploy-drift-dashboard",
      "title": "Deploy Drift Dashboard",
      "shortDescription": "Track main-vs-live drift, latest deploy status, and route health to keep autonomous releases reliable.",
      "status": "live",
      "href": "/ai-lab/deploy-drift-dashboard",
      "score": 69,
      "priority": "medium",
      "reason": "Useful candidate for incremental evolution cycle with gated validation."
    },
    {
      "id": "autonomous-funnel-orchestrator",
      "title": "Autonomous Funnel Orchestrator",
      "shortDescription": "Design smarter CTA, social proof, and funnel actions with weighted impact and confidence scoring for faster growth decisions.",
      "status": "live",
      "href": "/ai-lab/autonomous-funnel-orchestrator",
      "score": 68,
      "priority": "medium",
      "reason": "Useful candidate for incremental evolution cycle with gated validation."
    }
  ]
}