{
  "\"github-actions[bot]\"": {
    "scores": [
      0
    ],
    "trend": "neutral"
  },
  "\"There's An AI For That\"": {
    "scores": [
      0
    ],
    "trend": "neutral"
  },
  "Mail Delivery Subsystem": {
    "scores": [
      -1
    ],
    "trend": "neutral"
  },
  "Kleber Garcia Alcatrao": {
    "scores": [
      0,
      0,
      0
    ],
    "trend": "neutral"
  },
  "Zapier Alerts": {
    "scores": [
      0,
      0
    ],
    "trend": "neutral"
  },
  "Airbnb": {
    "scores": [
      0,
      0,
      0,
      0,
      0,
      0,
      0,
      0,
      0,
      0,
      0,
      0,
      0,
      0,
      0,
      0,
      0,
      0,
      0,
      0,
      0,
      0,
      0
    ],
    "trend": "neutral"
  },
  "Site Quality Monitoring Alert": {
    "scores": [
      -1
    ],
    "trend": "neutral"
  },
  "\"Edna (Airbnb)\"": {
    "scores": [
      0
    ],
    "trend": "neutral"
  },
  "BTG Pactual": {
    "scores": [
      0
    ],
    "trend": "neutral"
  },
  "Ax Belenus": {
    "scores": [
      0
    ],
    "trend": "neutral"
  },
  "Avenue": {
    "scores": [
      0
    ],
    "trend": "neutral"
  },
  "\"#TimeSIEG\"": {
    "scores": [
      0
    ],
    "trend": "neutral"
  },
  "Agilize Contabilidade Online": {
    "scores": [
      0,
      0
    ],
    "trend": "neutral"
  },
  "\"Carlos Alcatr\u00e3o\"": {
    "scores": [
      0
    ],
    "trend": "neutral"
  }
}